fuzzy_search/__init__.py
fuzzy_search/compare/spelling.py
fuzzy_search/fuzzy_searcher.py
fuzzy_search/match/__init__.py
fuzzy_search/match/candidate_match.py
fuzzy_search/match/exact_match.py
fuzzy_search/match/phrase_match.py
fuzzy_search/match/skip_match.py
fuzzy_search/pattern/__init__.py
fuzzy_search/pattern/fuzzy_patterns.py
fuzzy_search/pattern/fuzzy_template.py
fuzzy_search/phrase/__init__.py
fuzzy_search/phrase/phrase.py
fuzzy_search/phrase/phrase_model.py
fuzzy_search/search/__init__.py
fuzzy_search/search/config.py
fuzzy_search/search/context_searcher.py
fuzzy_search/search/phrase_searcher.py
fuzzy_search/search/searcher.py
fuzzy_search/search/template_searcher.py
fuzzy_search/search/token_searcher.py
fuzzy_search/similarity.py
fuzzy_search/stats/compare.py
fuzzy_search/stats/freq.py
fuzzy_search/tokenization/__init__.py
fuzzy_search/tokenization/string.py
fuzzy_search/tokenization/subtoken.py
fuzzy_search/tokenization/token.py
fuzzy_search/tokenization/vocabulary.py
fuzzy_search-2.6.0.dist-info/LICENSE
fuzzy_search-2.6.0.dist-info/METADATA
fuzzy_search-2.6.0.dist-info/WHEEL
fuzzy_search-2.6.0.dist-info/entry_points.txt
fuzzy_search-2.6.0.dist-info/RECORD
