Metadata-Version: 2.3
Name: fuzzy-search
Version: 2.6.0
Summary: Tool for fuzzy searching in texts with historical language use and OCR/HTR errors
Author: Marijn Koolen
Author-email: marijn.koolen@gmail.com
Requires-Python: >=3.8.1
Classifier: Development Status :: 4 - Beta
Classifier: Intended Audience :: Science/Research
Classifier: License :: OSI Approved :: MIT License
Classifier: Topic :: Scientific/Engineering
Classifier: Operating System :: OS Independent
Classifier: Programming Language :: Python :: 3
Requires-Dist: flake8 (>=7.1.1,<8.0.0)
Requires-Dist: levenshtein (>=0.24,<1.0)
Requires-Dist: nltk (>=3.9.1,<4.0.0)
Requires-Dist: numpy (>=1.20,<3.0.0)
Requires-Dist: pytest (>=8.3.4,<9.0.0)
Project-URL: Bug Tracker, https://github.com/marijnkoolen/fuzzy-search/issues
